BottleOIDC/JWKS.py
BottleOIDC/__init__.py
BottleOIDC/botOIDC.py
BottleOIDC/bottle_utils.py
BottleOIDC/oidc_discover.py
BottleOIDC/oidc_state.py
BottleOIDC-21.8.30.data/data/examples/app.py
BottleOIDC-21.8.30.data/data/examples/config_template.py
BottleOIDC-21.8.30.dist-info/LICENSE.txt
BottleOIDC-21.8.30.dist-info/METADATA
BottleOIDC-21.8.30.dist-info/WHEEL
BottleOIDC-21.8.30.dist-info/top_level.txt
BottleOIDC-21.8.30.dist-info/RECORD
